echeck/Curlclient.py
echeck/Properties.py
echeck/__init__.py
echeck/card_vd.py
echeck/ec_bin.py
echeck/ec_exception.py
echeck/enums.py
echeck/eping.py
echeck/escan.py
echeck/eshell.py
echeck/interactive.py
echeck/spider.py
echeck/telnet_client.py
echeck/conf/__init__.py
echeck/conf/config.py
echeck/log/Logger.py
echeck/log/__init__.py
echeck/wrapped/__init__.py
echeck/wrapped/pretty_decorator.py
test/__init__.py
test/echeck_test.py
echeck-2.0.5.dist-info/LICENSE
echeck-2.0.5.dist-info/METADATA
echeck-2.0.5.dist-info/WHEEL
echeck-2.0.5.dist-info/entry_points.txt
echeck-2.0.5.dist-info/top_level.txt
echeck-2.0.5.dist-info/zip-safe
echeck-2.0.5.dist-info/RECORD
