Metadata-Version: 2.1
Name: echeck
Version: 2.0.5
Summary: 简单易用的批量环境检查工具
Home-page: https://github.com/rockyCheung/easy_echeck.git
Author: Rocky
Author-email: 274935730@qq.com
License: PSF
Platform: UNKNOWN
Classifier: License :: OSI Approved :: MIT License
Classifier: Programming Language :: Python
Classifier: Intended Audience :: Developers
Classifier: Operating System :: OS Independent
Classifier: Programming Language :: Python :: 3
Classifier: Programming Language :: Python :: 3.3
Classifier: Programming Language :: Python :: 3.4
Classifier: Programming Language :: Python :: 3.5
Classifier: Programming Language :: Python :: 3.6
Classifier: Programming Language :: Python :: 3.7
Classifier: Programming Language :: Python :: 3 :: Only
Requires-Python: >=3
Requires-Dist: pycurl (>=7.43.0.2)
Requires-Dist: beautifulsoup4 (>=4.7.1)
Requires-Dist: soupsieve (>=1.8)
Requires-Dist: wheel (>=0.33.1)
Requires-Dist: setuptools (>=40.8.0)
Requires-Dist: PyYAML (>=3.13)
Requires-Dist: nmap (>=0.0.1)
Requires-Dist: paramiko (>=2.4.2)
Requires-Dist: asn1crypto (>=0.24.0)
Requires-Dist: bcrypt (>=3.1.6)
Requires-Dist: cffi (>=1.12.2)
Requires-Dist: cryptography (>=2.4.2)
Requires-Dist: pyasn1 (>=0.4.5)
Requires-Dist: pycparser (>=2.19)
Requires-Dist: pynacl (>=1.3.0)
Requires-Dist: six (>=1.12.0)
Requires-Dist: pytest (>=4.3.1)
Requires-Dist: wrapt (>=1.11.1)
